Workbook

Sheet Assumptions
A1: Editable Commercial Assumptions
A2: Blue cells are inputs. All profitability sheets refer back to these values.
A4: Input | B4: Value | C4: Unit / note
A5: USD to PKR planning rate | B5: 280 | C5: Editable planning rate; not an accounting quote
A6: Global delivery labor cost | B6: 20 | C6: USD per direct support hour
A7: Pakistan delivery labor cost | B7: 10 | C7: USD per direct support hour
A8: ElevenLabs additional minute | B8: 0.08 | C8: USD/min; LLM and telephony separate
A9: Gemini 2.5 Flash via ElevenLabs | B9: 0.0012 | C9: USD/min planning estimate from ElevenLabs calculator
A10: US inbound local telephony | B10: 0.0085 | C10: USD/min; carrier pass-through
A11: Pakistan outbound landline | B11: 0.155 | C11: USD/min; carrier pass-through
A12: Pakistan outbound mobile | B12: 0.18 | C12: USD/min; carrier pass-through
A13: Annual prepay discount | B13: 0.1 | C13: 10% off recurring service
A14: Target standard gross margin | B14: 0.7 | C14: After direct platform and delivery labor
A15: Contingency on platform spend | B15: 0.1 | C15: Cost variance and test-call reserve

Sheet Client Pricing
A1: Recommended Managed-Service Pricing
A2: Usage allowances exclude PSTN carrier charges. Carrier costs should be passed through at cost plus 15-20% administration.
A4: Tier | B4: Best fit | C4: Locations | D4: Included AI minutes | E4: Setup USD | F4: Monthly USD | G4: Setup PKR | H4: Monthly PKR | I4: Overage USD/min | J4: Term
A5: Launch | B5: Single restaurant / clinic / small service firm | C5: 1 | D5: 300 | E5: 1500 | F5: 497 | G5: 250000 | H5: 99000 | I5: 0.25 | J5: 3-month minimum
A6: Growth | B6: Busy location or 2 locations; orders + reservations | C6: 1-2 | D6: 1000 | E6: 3000 | F6: 997 | G6: 500000 | H6: 225000 | I6: 0.22 | J6: 6-month minimum
A7: Scale | B7: Multi-location operator with integrations and QA | C7: 3-5 | D7: 3000 | E7: 6000 | F7: 1997 | G7: 1000000 | H7: 450000 | I7: 0.18 | J7: 12-month recommended
A8: Enterprise | B8: Franchise / contact-center replacement | C8: 6+ | D8: 8000 | E8: 12000 | F8: 4997 | G8: 2000000 | H8: 1100000 | I8: 0.16 | J8: Annual contract
A11: Commercial rules
A12: • Never waive discovery and setup without receiving a 12-month commitment; discount it up to 50% instead.
A13: • Bill platform overages monthly; send alerts at 70%, 85%, and 100% of allowance.
A14: • Do not include unlimited custom development. Sell change packs or scope a new project.
A15: • Price telephony separately because country and direction can change carrier cost by more than 20x.
A16: • Charge each additional location 35-60% of the base tier depending on shared menu, workflows, and reporting.

Sheet Unit Economics
A1: Monthly Unit Economics — Global List Price
A2: Direct COGS includes platform allocation, direct support labor, monitoring, and contingency; sales/marketing and corporate overhead are excluded.
A4: Tier | B4: Revenue | C4: AI plan + LLM | D4: Data/automation/hosting | E4: Email/monitoring | F4: Support labor | G4: Contingency | H4: Total direct COGS | I4: Gross profit | J4: Gross margin
A5: Launch | B5: 497 | C5: 24.36 | D5: 55 | E5: 10 | F5: 60 | G5: =SUM(C5:E5)*Assumptions!$B$15 | H5: =SUM(C5:G5) | I5: =B5-H5 | J5: =I5/B5
A6: Growth | B6: 997 | C6: 100.2 | D6: 65 | E6: 20 | F6: 120 | G6: =SUM(C6:E6)*Assumptions!$B$15 | H6: =SUM(C6:G6) | I6: =B6-H6 | J6: =I6/B6
A7: Scale | B7: 1997 | C7: 302.6 | D7: 120 | E7: 40 | F7: 240 | G7: =SUM(C7:E7)*Assumptions!$B$15 | H7: =SUM(C7:G7) | I7: =B7-H7 | J7: =I7/B7
A8: Enterprise | B8: 4997 | C8: 999.6 | D8: 280 | E8: 100 | F8: 600 | G8: =SUM(C8:E8)*Assumptions!$B$15 | H8: =SUM(C8:G8) | I8: =B8-H8 | J8: =I8/B8

Sheet Platform Costs
A1: Technology Cost Map
A2: Official public list prices checked 13 July 2026. Always reconfirm before signing a long-term client contract.
A4: Platform | B4: Role | C4: Pricing method | D4: Relevant public price | E4: Cost driver | F4: Recommended use | G4: Cost-control action | H4: Source
A5: ElevenLabs Agents | B5: Voice, STT, TTS, orchestration | C5: Plan + included minutes + overage | D5: $6/75m; $22/275m; $99/1,238m; $299/3,738m; $990/12,375m; $0.08 extra | E5: Minutes and concurrency | F5: Primary quality voice stack | G5: Pool responsibly; shorten prompts; end dead calls; alert on burst usage | H5: elevenlabs.io/pricing/agents
A6: Gemini 2.5 Flash | B6: Agent reasoning / app chat | C6: Tokens; ElevenLabs shows per-minute model estimate | D6: $0.30/M input and $2.50/M output tokens; approx $0.0012/min inside ElevenLabs calculator | E6: Prompt/output tokens | F6: Fast multilingual reasoning | G6: Keep system prompt concise; cache stable context; use Flash-Lite for offline classification | H6: ai.google.dev/gemini-api/docs/pricing
A7: Supabase | B7: Postgres, auth, storage | C7: Plan + compute + overages | D7: Pro from $25/mo; first micro compute covered; extra projects from $10 | E7: Projects, compute, MAU, storage, egress | F7: Separate production data per premium client | G7: Start micro; archive audio externally; enforce retention; index queries | H7: supabase.com/pricing
A8: n8n Cloud | B8: Orders, reservations, CRM/email workflows | C8: Completed workflow executions | D8: €20/mo annual 2.5k executions; €50/mo annual 10k | E8: Executions and concurrency | F8: Shared agency automation with client separation | G8: One event per workflow; avoid polling; aggregate steps into one execution | H8: n8n.io/pricing
A9: Vercel | B9: Web app and API hosting | C9: Seat + included usage + overages | D9: Pro $20/mo with $20 usage credit | E9: Seats, compute, traffic, analytics | F9: Production hosting | G9: Cache reads; static assets; spend caps; separate enterprise teams only when required | H9: vercel.com/pricing
A10: Resend | B10: Transactional confirmations | C10: Emails/month | D10: Free 3k; Pro $20/50k; $0.90 per extra 1k | E10: Email count and domains | F10: Reliable order/reservation emails | G10: Pool domains on Pro; maintain SPF/DKIM/DMARC; suppress bounces | H10: resend.com/pricing
A11: Twilio US | B11: PSTN number and calls | C11: Number + per minute | D11: $1.15 local number; $0.0085 inbound; $0.014 outbound | E11: Country, direction, duration | F11: Phone deployment for US clients | G11: Pass through; use local inbound; negotiate volume at scale | H11: twilio.com/en-us/voice/pricing/us
A12: Twilio Pakistan | B12: PSTN outbound / SIP | C12: Per minute; local availability varies | D12: $0.155 landline; $0.18 mobile outbound | E12: Destination and carrier | F12: Fallback only until local SIP is contracted | G12: Do not bundle; source local SIP; use BYOC when commercially viable | H12: twilio.com/voice/pricing/pk

Sheet Market Benchmarks
A1: Global Pricing Benchmarks
A2: Productized voice platforms, managed receptionists, and agency market benchmarks are different categories; use them to frame value, not as identical substitutes.
A4: Provider | B4: Category | C4: Published price | D4: Usage included / basis | E4: Setup | F4: What it proves | G4: Source
A5: Goodcall | B5: Self-serve AI phone agent | C5: $79 / $129 / $249 per agent monthly | D5: 100 / 250 / 500 unique customers; $0.50 extra customer | E5: Self-serve | F5: Low-end anchor is software only, not custom managed operations | G5: goodcall.com/pricing
A6: Smith.ai | B6: Hybrid managed receptionist | C6: $300 / $810 / $2,100 monthly | D6: 30 / 90 / 300 calls | E6: Included onboarding | F6: Businesses pay substantially for accountable call handling | G6: smith.ai/receptionists
A7: WildRun AI | B7: Managed AI receptionist agency | C7: $497 / $997 / $1,997 monthly | D7: 500 min on Starter; higher tiers | E7: $1,500 Starter | F7: Validates setup + managed monthly tiers near our global proposal | G7: wildrunai.com/pricing
A8: My AI Front Desk | B8: White-label reseller platform | C8: $54.99 wholesale example; resellers sell $400+ | D8: Wholesale and rebilling | E8: Varies | F8: Margin comes from packaging, brand, configuration, and service | G8: myaifrontdesk.com/white-label
A9: Retell AI | B9: Developer voice platform | C9: $0.07-$0.31/min | D9: Pay as you go; 20 concurrent calls | E9: Developer setup | F9: Raw infrastructure cost is not the client value | G9: retellai.com/pricing
A10: Vapi | B10: Developer voice platform | C10: $0.05/min platform fee | D10: Providers and telephony additional | E10: Developer setup | F10: Composable stack; provider costs must be added | G10: vapi.ai/pricing
A11: Bland AI | B11: Developer voice platform | C11: $0.14/min free; $299+$0.12; $499+$0.11 | D11: Voice stack included; telephony varies | E11: Developer setup | F11: Scale discounts lower raw cost, but service still required | G11: bland.ai/pricing
A12: Synthflow | B12: Enterprise voice platform | C12: Enterprise from $30,000/year | D12: Volume, concurrency, support, security | E12: Sales-led | F12: Enterprise buyers purchase reliability and governance | G12: synthflow.ai/pricing
A13: Clutch AI firms | B13: Custom AI development market | C13: $24-$49/hour common; projects $10k-$49,999 | D13: Average reviewed project much higher | E13: Project based | F13: Custom AI work supports strong implementation fees | G13: clutch.co/developers/artificial-intelligence/pricing

Sheet Support and SLA
A1: Monthly Service Scope and Retention Engine
A2: Support is an operating product: monitor, measure, improve, and prove value every month.
A4: Tier | B4: Monitoring | C4: Conversation QA | D4: Optimization | E4: Reporting | F4: Included change time | G4: Critical response target | H4: Business review
A5: Launch | B5: Business-day alerts | C5: 10 calls/month | D5: 1 prompt/KB tune | E5: Monthly scorecard | F5: 1 hour | G5: Next business day | H5: Quarterly
A6: Growth | B6: Daily automated checks | C6: 25 calls/month | D6: 2 tune cycles | E6: Monthly ROI report | F6: 3 hours | G6: 8 business hours | H6: Monthly
A7: Scale | B7: 24/7 technical alerts | C7: 75 calls/month + failure review | D7: Weekly tuning | E7: Location + funnel report | F7: 6 hours | G7: 4 hours | H7: Monthly
A8: Enterprise | B8: 24/7 on-call monitoring | C8: Risk-based sample + automated evals | D8: Continuous release cadence | E8: Executive + operational dashboards | F8: 12 hours | G8: 1 hour Sev-1 acknowledgement | H8: Monthly + quarterly roadmap
A11: Monthly value proof
A12: • Calls/conversations handled
A13: • Orders/reservations completed
A14: • Completion and transfer rate
A15: • Estimated revenue captured
A16: • Average response latency
A17: • Top failure reasons
A18: • Human hours saved
A19: • Changes shipped

Sheet Agency Forecast
A1: Illustrative Portfolio Forecast
A2: Editable client mix. This is contribution margin before sales, management, tax, and corporate overhead.
A4: Scenario | B4: Launch clients | C4: Growth clients | D4: Scale clients | E4: Enterprise clients | F4: MRR | G4: Direct COGS | H4: Gross profit | I4: Gross margin | J4: ARR
A5: Early traction | B5: 3 | C5: 2 | D5: 0 | E5: 0 | F5: =B5*'Unit Economics'!B5+C5*'Unit Economics'!B6+D5*'Unit Economics'!B7+E5*'Unit Economics'!B8 | G5: =B5*'Unit Economics'!H5+C5*'Unit Economics'!H6+D5*'Unit Economics'!H7+E5*'Unit Economics'!H8 | H5: =F5-G5 | I5: =H5/F5 | J5: =F5*12
A6: Product-market fit | B6: 8 | C6: 7 | D6: 3 | E6: 0 | F6: =B6*'Unit Economics'!B5+C6*'Unit Economics'!B6+D6*'Unit Economics'!B7+E6*'Unit Economics'!B8 | G6: =B6*'Unit Economics'!H5+C6*'Unit Economics'!H6+D6*'Unit Economics'!H7+E6*'Unit Economics'!H8 | H6: =F6-G6 | I6: =H6/F6 | J6: =F6*12
A7: Scaled agency | B7: 15 | C7: 20 | D7: 10 | E7: 2 | F7: =B7*'Unit Economics'!B5+C7*'Unit Economics'!B6+D7*'Unit Economics'!B7+E7*'Unit Economics'!B8 | G7: =B7*'Unit Economics'!H5+C7*'Unit Economics'!H6+D7*'Unit Economics'!H7+E7*'Unit Economics'!H8 | H7: =F7-G7 | I7: =H7/F7 | J7: =F7*12
A8: Regional leader | B8: 25 | C8: 40 | D8: 25 | E8: 5 | F8: =B8*'Unit Economics'!B5+C8*'Unit Economics'!B6+D8*'Unit Economics'!B7+E8*'Unit Economics'!B8 | G8: =B8*'Unit Economics'!H5+C8*'Unit Economics'!H6+D8*'Unit Economics'!H7+E8*'Unit Economics'!H8 | H8: =F8-G8 | I8: =H8/F8 | J8: =F8*12

Sheet Sales Playbook
A1: How to Sell and Scale
A2: Niche-first, proof-led, recurring managed service.
A4: Stage | B4: Action | C4: Asset / KPI | D4: Commercial rule | E4: Scaling mechanism
A5: Choose niche | B5: Start with restaurants, then adjacent appointment-led businesses | C5: One repeatable demo and ROI calculator | D5: Do not customize the core for every prospect | E5: Reusable prompts, workflows, onboarding checklist
A6: Lead generation | B6: Target missed-call pain, peak-hour overflow, and slow booking response | C6: 50 named accounts/week; 10 demos/month | D6: Sell a paid pilot or annual plan | E6: Outbound, referrals, POS/CRM partners
A7: Discovery | B7: Measure calls, minutes, completion, average ticket, labor and failure cost | C7: Baseline business case | D7: Price by value and volume, not vendor bill | E7: Standard discovery form
A8: Pilot | B8: Run one location/use case for 30-45 days | C8: Completion >85%; error budget; revenue captured | D8: Setup paid; clear acceptance criteria | E8: Reusable test suite and launch gate
A9: Expansion | B9: Add channels, workflows, locations, languages and outbound campaigns | C9: Net revenue retention >110% | D9: Per-location and module add-ons | E9: Land-and-expand roadmap
A10: Retention | B10: Monthly QA, ROI report, tuning and roadmap | C10: Logo churn <2% monthly; gross margin >65% | D10: Annual prepay 10% discount | E10: Customer success cadence
A11: Operations | B11: Central monitoring with separate client data and secrets | C11: Incidents, latency, task success | D11: No shared credentials with clients | E11: Templates, automated evaluations, runbooks

Sheet Sources
A1: Research Sources
A2: Primary vendor pages were preferred for tool pricing. Agency benchmarks include published provider pages and Clutch's reviewed marketplace data.
A4: Topic | B4: URL | C4: Checked | D4: Notes
A5: ElevenLabs Agents | B5: https://elevenlabs.io/pricing/agents | C5: 2026-07-13 | D5: Plans, minutes, concurrency, overage
A6: Gemini API | B6: https://ai.google.dev/gemini-api/docs/pricing | C6: 2026-07-13 | D6: Token prices
A7: Supabase | B7: https://supabase.com/pricing | C7: 2026-07-13 | D7: Plan, project, compute and overages
A8: n8n | B8: https://n8n.io/pricing/ | C8: 2026-07-13 | D8: Execution-based cloud pricing
A9: Vercel | B9: https://vercel.com/pricing | C9: 2026-07-13 | D9: Pro and usage model
A10: Resend | B10: https://resend.com/pricing | C10: 2026-07-13 | D10: Transactional email
A11: Twilio US | B11: https://www.twilio.com/en-us/voice/pricing/us | C11: 2026-07-13 | D11: Inbound/outbound and number
A12: Twilio Pakistan | B12: https://www.twilio.com/voice/pricing/pk | C12: 2026-07-13 | D12: Outbound rates; availability varies
A13: Goodcall | B13: https://www.goodcall.com/pricing | C13: 2026-07-13 | D13: Self-serve competitor
A14: Smith.ai | B14: https://smith.ai/receptionists | C14: 2026-07-13 | D14: Managed receptionist benchmark
A15: Retell AI | B15: https://www.retellai.com/pricing | C15: 2026-07-13 | D15: Voice infrastructure benchmark
... A21: Clutch AI pricing | B21: https://clutch.co/developers/artificial-intelligence/pricing | C21: 2026-07-13 | D21: Global custom development benchmark
